LICENSE
MANIFEST.in
NOTICE
README.md
requirements.txt
setup.cfg
setup.py
pyizzy/__init__.py
pyizzy/__main__.py
pyizzy/assistant.py
pyizzy/config.py
pyizzy/decorator.py
pyizzy/exceptions.py
pyizzy/xd.py
pyizzy.egg-info/PKG-INFO
pyizzy.egg-info/SOURCES.txt
pyizzy.egg-info/dependency_links.txt
pyizzy.egg-info/requires.txt
pyizzy.egg-info/top_level.txt
pyizzy/Clients/__init__.py
pyizzy/Clients/client.py
pyizzy/Clients/startup.py
pyizzy/dB/__init__.py
pyizzy/dB/_core.py
pyizzy/dB/afk_db.py
pyizzy/dB/antiflood_db.py
pyizzy/dB/asst_fns.py
pyizzy/dB/asstcmd_db.py
pyizzy/dB/autoban_db.py
pyizzy/dB/blacklist_chat_db.py
pyizzy/dB/blacklist_db.py
pyizzy/dB/botchat_db.py
pyizzy/dB/broadcast_db.py
pyizzy/dB/ch_db.py
pyizzy/dB/dnd_db.py
pyizzy/dB/echo_db.py
pyizzy/dB/filestore_db.py
pyizzy/dB/filter_db.py
pyizzy/dB/forcesub_db.py
pyizzy/dB/gban_mute_db.py
pyizzy/dB/gcast_blacklist_db.py
pyizzy/dB/greetings_db.py
pyizzy/dB/logusers_db.py
pyizzy/dB/mute_db.py
pyizzy/dB/night_db.py
pyizzy/dB/notes_db.py
pyizzy/dB/nsfw_db.py
pyizzy/dB/pmpermit_db.py
pyizzy/dB/snips_db.py
pyizzy/dB/vc_sudos.py
pyizzy/dB/warn_db.py
pyizzy/methods/__init__.py
pyizzy/methods/_database.py
pyizzy/methods/_misc.py
pyizzy/methods/converter.py
pyizzy/methods/func.py
pyizzy/methods/helpers.py
pyizzy/methods/hosting.py
pyizzy/methods/queue.py
pyizzy/pyrogram/__init__.py
pyizzy/pyrogram/_wrappers.py
pyizzy/pyrogram/func.py
pyizzy/pyrogram/misc.py
pyizzy/pyrogram/pastebin.py
pyizzy/pyrogram/sections.py
pyizzy/pyrogram/toolbot.py
pyizzy/pyrogram/tools.py
pyizzy/resources/__init__.py
pyizzy/telethon/__init__.py
pyizzy/telethon/dB/__init__.py
pyizzy/telethon/dB/_core.py
pyizzy/telethon/dB/afk_db.py
pyizzy/telethon/dB/antiflood_db.py
pyizzy/telethon/dB/asst_fns.py
pyizzy/telethon/dB/asstcmd_db.py
pyizzy/telethon/dB/autoban_db.py
pyizzy/telethon/dB/blacklist_chat_db.py
pyizzy/telethon/dB/blacklist_db.py
pyizzy/telethon/dB/botchat_db.py
pyizzy/telethon/dB/broadcast_db.py
pyizzy/telethon/dB/ch_db.py
pyizzy/telethon/dB/dnd_db.py
pyizzy/telethon/dB/echo_db.py
pyizzy/telethon/dB/filestore_db.py
pyizzy/telethon/dB/filter_db.py
pyizzy/telethon/dB/forcesub_db.py
