Metadata-Version: 2.1
Name: pyizzy
Version: 0.3.1
Summary: A Secure and Powerful Python-Pyrogram Based Library For Geez RAM.
Home-page: https://github.com/hitokizzy/pyizzy
Author: hitokizzy
Author-email: hitokizzy@gmail.com
License: GNU General Public License v3.0 (GPL-3.0)
Project-URL: Bug Tracker, https://github.com/hitokizzy/pyizzy/issues
Project-URL: Source Code, https://github.com/hitokizzy/pyizzy
Platform: UNKNOWN
Classifier: Programming Language :: Python :: 3
Classifier: Programming Language :: Python :: 3.8
Classifier: Programming Language :: Python :: 3.9
Classifier: Programming Language :: Python :: 3.10
Classifier: Programming Language :: Python :: 3.11
Classifier: License :: OSI Approved :: GNU General Public License v3 (GPLv3)
Classifier: Operating System :: OS Independent
Requires-Python: ~=3.7
License-File: LICENSE
License-File: NOTICE
